pypulsepal/__init__.py
pypulsepal/definitions.py
pypulsepal/pulsepal.py
pypulsepal/utils.py
pypulsepal/write_tests.py
pypulsepal-0.0.1.dist-info/LICENSE
pypulsepal-0.0.1.dist-info/METADATA
pypulsepal-0.0.1.dist-info/WHEEL
pypulsepal-0.0.1.dist-info/top_level.txt
pypulsepal-0.0.1.dist-info/RECORD
